clisrc/__init__.py
clisrc/clipython.py
clisrc/commandLineInterface.py
cli_python-0.0.1.dist-info/METADATA
cli_python-0.0.1.dist-info/WHEEL
cli_python-0.0.1.dist-info/top_level.txt
cli_python-0.0.1.dist-info/RECORD
