Metadata-Version: 2.1
Name: cli-python
Version: 0.0.1
Summary: An easy way to use the command line interface of a Python package
Home-page: 
Author: Andre Vieira da Silva
Author-email: andsilvadrcc@gmail.com
Classifier: Programming Language :: Python :: 3
Classifier: License :: OSI Approved :: MIT License
Classifier: Operating System :: OS Independent
Requires-Python: >=3.6
